odoo/addons/product_code_unique/README.rst
odoo/addons/product_code_unique/__init__.py
odoo/addons/product_code_unique/__manifest__.py
odoo/addons/product_code_unique/hook.py
odoo/addons/product_code_unique/i18n/ca.po
odoo/addons/product_code_unique/i18n/de.po
odoo/addons/product_code_unique/i18n/es.po
odoo/addons/product_code_unique/i18n/fr.po
odoo/addons/product_code_unique/i18n/fr_FR.po
odoo/addons/product_code_unique/i18n/it.po
odoo/addons/product_code_unique/i18n/product_code_unique.pot
odoo/addons/product_code_unique/i18n/pt.po
odoo/addons/product_code_unique/i18n/sk.po
odoo/addons/product_code_unique/models/__init__.py
odoo/addons/product_code_unique/models/product.py
odoo/addons/product_code_unique/readme/CONTRIBUTORS.md
odoo/addons/product_code_unique/readme/DESCRIPTION.md
odoo/addons/product_code_unique/readme/ROADMAP.md
odoo/addons/product_code_unique/readme/USAGE.md
odoo/addons/product_code_unique/static/description/icon.png
odoo/addons/product_code_unique/static/description/index.html
odoo/addons/product_code_unique/tests/__init__.py
odoo/addons/product_code_unique/tests/test_code_unique.py
odoo_addon_product_code_unique-18.0.1.0.0.4.dist-info/METADATA
odoo_addon_product_code_unique-18.0.1.0.0.4.dist-info/WHEEL
odoo_addon_product_code_unique-18.0.1.0.0.4.dist-info/top_level.txt
odoo_addon_product_code_unique-18.0.1.0.0.4.dist-info/RECORD
